cofitestsuite/__init__.py
cofitestsuite/_version.py
cofitestsuite/earthquakebootstrap/__init__.py
cofitestsuite/earthquakebootstrap/border.pickle
cofitestsuite/earthquakebootstrap/earthquakebootstrap.py
cofitestsuite/earthquakebootstrap/eqlocate.py
cofitestsuite/earthquakebootstrap/loctim.pickle
cofitestsuite/earthquakebootstrap/plotcovellipse.py
cofitestsuite/earthquakeleastsquares/__init__.py
cofitestsuite/earthquakeleastsquares/earthquakeleastsquares.py
cofitestsuite/earthquakeleastsquares/eqdata.pickle
cofitestsuite/earthquakeleastsquares/eqlocate.py
cofitestsuite/earthquakeleastsquares/loctim.pickle
cofitestsuite/earthquakeleastsquares/plotcovellipse.py
cofitestsuite/gravityforward/Model_1d.npy
cofitestsuite/gravityforward/__init__.py
cofitestsuite/gravityforward/gravityforward.py
cofitestsuite/xraytomography/__init__.py
cofitestsuite/xraytomography/xraytomography.py
cofitestsuite/xraytomography/xrt_data.dat
cofitestsuite-0.12.dist-info/LICENSE
cofitestsuite-0.12.dist-info/METADATA
cofitestsuite-0.12.dist-info/WHEEL
cofitestsuite-0.12.dist-info/top_level.txt
cofitestsuite-0.12.dist-info/RECORD
