Metadata-Version: 2.1
Name: cofitestsuite
Version: 0.12
Summary: A gravity forward calculation
Home-page: https://github.com/pypa/sampleproject
Author: Hannes
Author-email: hannes.hollmann@anu.edu.au
License: BSD 2-clause
Project-URL: Bug Tracker, https://github.com/pypa/sampleproject/issues
Platform: UNKNOWN
Classifier: Development Status :: 1 - Planning
Classifier: Intended Audience :: Science/Research
Classifier: License :: OSI Approved :: BSD License
Classifier: Programming Language :: Python :: 2
Classifier: Programming Language :: Python :: 2.7
Classifier: Programming Language :: Python :: 3
Classifier: Programming Language :: Python :: 3.4
Classifier: Programming Language :: Python :: 3.5
Requires-Python: >=3.6
License-File: LICENSE
Requires-Dist: numpy
